Booth_Seq_Multiplier.v
module Booth_Seq_Multiplier(
    // Control signals
    input clk,       // Clock signal
    input load,      // Load input values
    input reset,     // Reset signal

    // Input operands
    input [3:0] M,   // Multiplicand (4-bit)
    input [3:0] Q,   // Multiplier (4-bit)
    
    // Output product
    output reg [7:0] P  // Product (8-bit)
);
    // Internal registers
    reg [3:0] A = 4'b0;           // Accumulator for partial products
    reg Q_minus_one = 0;          // Previous bit of Q (Q[-1])
    reg [3:0] Q_temp = 4'b0;      // Working copy of multiplier
    reg [3:0] M_temp = 4'b0;      // Working copy of multiplicand
    reg [2:0] Count = 3'd4;       // Iteration counter
    
    // Main operation - Booth algorithm
    always @ (posedge clk) begin
        // Reset operation
        if (reset == 1) begin
            A = 4'b0;             // Clear accumulator
            Q_minus_one = 0;      // Clear Q[-1]
            P = 8'b0;             // Clear product
            Q_temp = 4'b0;        // Clear temp multiplier
            M_temp = 4'b0;        // Clear temp multiplicand
            Count = 3'd4;         // Reset counter to 4 iterations
        end
        // Load operation
        else if (load == 1) begin
            Q_temp = Q;           // Load multiplier
            M_temp = M;           // Load multiplicand
        end
        // Booth algorithm operations - based on Q0 and Q-1
        else if ((Q_temp[0] == Q_minus_one) && (Count > 3'd0)) begin
            // Case 00 or 11: Only shift (no add/sub)
            Q_minus_one = Q_temp[0];
            Q_temp = {A[0], Q_temp[3:1]};  // Right shift Q
            A = {A[3], A[3:1]};           // Arithmetic right shift A
            Count = Count - 1'b1;
        end
        else if ((Q_temp[0] == 0 && Q_minus_one == 1) && (Count > 3'd0)) begin
            // Case 01: Add then shift
            A = A + M_temp;
            Q_minus_one = Q_temp[0];
            Q_temp = {A[0], Q_temp[3:1]};  // Right shift Q
            A = {A[3], A[3:1]};           // Arithmetic right shift A
            Count = Count - 1'b1;
        end
        else if ((Q_temp[0] == 1 && Q_minus_one == 0) && (Count > 3'd0)) begin
            // Case 10: Subtract then shift
            A = A - M_temp;
            Q_minus_one = Q_temp[0];
            Q_temp = {A[0], Q_temp[3:1]};  // Right shift Q
            A = {A[3], A[3:1]};           // Arithmetic right shift A
            Count = Count - 1'b1;
        end
        else begin
            // Algorithm completed or invalid state
            Count = 3'b0;
        end
        
        // Assign final product
        P = {A, Q_temp};
    end
endmodule

Booth_Seq_Multiplier_tb.v
`timescale 1ns/ 1ps

module Booth_Seq_Multiplier_tb;

    // Inputs
    reg clk;
    reg load;
    reg reset;
    reg [3:0] M;
    reg [3:0] Q;

    // Outputs
    wire [7:0] P;
    
    // Internal signals for monitoring
    wire [3:0] A_monitor;
    wire Q_minus_one_monitor;
    wire [3:0] Q_temp_monitor;
    wire [2:0] Count_monitor;
    
    // Iteration counter for display
    integer iter_count = 0;
    reg [2:0] prev_count = 0;  // 添加這行來定義先前的計數值

    // Clock period definition
    parameter CLOCK_PERIOD = 20;

    // Instantiate the Unit Under Test (UUT)
    Booth_Seq_Multiplier dut (
        .clk(clk), 
        .load(load), 
        .reset(reset), 
        .M(M), 
        .Q(Q), 
        .P(P)
    );
    
    // For debug monitoring
    assign A_monitor = dut.A;
    assign Q_minus_one_monitor = dut.Q_minus_one;
    assign Q_temp_monitor = dut.Q_temp;
    assign Count_monitor = dut.Count;
    
    // Clock generation
    always #(CLOCK_PERIOD/2) clk = ~clk;
    
    // Time tracking
    time start_time, end_time;
    reg done_flag = 0;
    
    // Monitor multiplication progress
    always @(posedge clk) begin

        if (reset) begin
            done_flag = 0;
            iter_count = 0;
            prev_count = 0;  // 在reset時重置prev_count
        end

        if (load && !done_flag) begin
            start_time = $time;
            iter_count = 0;
            prev_count = 4;  // 初始化為4，因為Count從4開始
            $display("Time: %0t ns - Starting multiplication: %0d x %0d", 
                     $time, $signed(M), $signed(Q));
        end
        
        if (!reset && !load && Count_monitor != 0 && Count_monitor != prev_count) begin
            iter_count = 4 - Count_monitor;
            $display("Time: %0t ns - Iteration %0d: A=%b, Q=%b, Q[-1]=%b", 
                    $time, iter_count, A_monitor, Q_temp_monitor, Q_minus_one_monitor);
            prev_count = Count_monitor;  // 更新prev_count
        end
        
        if (!reset && !load && Count_monitor == 0 && !done_flag) begin
            end_time = $time;
            done_flag = 1;
            $display("Time: %0t ns - Multiplication complete!", $time);
            $display("Time: %0t ns - Final result: %0d x %0d = %0d (binary: %b)", 
                    $time, $signed(M), $signed(Q), $signed(P), P);
            $display("Time: %0t ns - Computation took %0d clock cycles (%0d ns)", 
                    $time, (end_time-start_time)/CLOCK_PERIOD, (end_time-start_time));
        end
    end
  
    // Test case execution
    initial begin
        // Initialize waveform dumps
        $dumpfile("booth_multiplier.vcd");
        $dumpvars(0, Booth_Seq_Multiplier_tb);
        
        // Test case title
        $display("====== BOOTH SEQUENTIAL MULTIPLIER TESTBENCH ======");
        
        // Initialize Inputs
        clk = 0;
        load = 0;
        reset = 1;
        M = 0;
        Q = 0;
        done_flag = 0;
        prev_count = 0;  // 初始化prev_count
        
        // Wait for global reset
        #(CLOCK_PERIOD*2);
        
        // Test Case 1: Positive x Positive (5 x 3 = 15)
        reset = 1;
        #CLOCK_PERIOD;
        reset = 0;
        M = 4'b0101;  // 5 in decimal
        Q = 4'b0011;  // 3 in decimal
        load = 1;
        #CLOCK_PERIOD;
        load = 0;
        
        // Wait for multiplication to complete
        wait(Count_monitor == 0);
        #(CLOCK_PERIOD*2);
        
        // Test Case 2: Negative x Positive (-5 x 3 = -15)
        reset = 1;
        #CLOCK_PERIOD;
        reset = 0;
        M = 4'b1011;  // -5 in 2's complement
        Q = 4'b0011;  // 3 in decimal
        load = 1;
        #CLOCK_PERIOD;
        load = 0;
        
        // Wait for multiplication to complete
        wait(Count_monitor == 0);
        #(CLOCK_PERIOD*2);
        
        // Test Case 3: Negative x Negative (-6 x -5 = 30)
        reset = 1;
        #CLOCK_PERIOD;
        reset = 0;
        M = 4'b1010;  // -6 in 2's complement
        Q = 4'b1011;  // -5 in 2's complement
        load = 1;
        #CLOCK_PERIOD;
        load = 0;
        
        // Wait for multiplication to complete
        wait(Count_monitor == 0);
        #(CLOCK_PERIOD*2);
        
        // End simulation
        $display("====== SIMULATION COMPLETE ======");
        $finish;
    end
endmodule

booth_multiplier.vcd
$date
	Thu Apr 17 03:22:11 2025
$end
$version
	Icarus Verilog
$end
$timescale
	1ps
$end
$scope module Booth_Seq_Multiplier_tb $end
$var wire 4 ! A_monitor [3:0] $end
$var wire 3 " Count_monitor [2:0] $end
$var wire 1 # Q_minus_one_monitor $end
$var wire 4 $ Q_temp_monitor [3:0] $end
$var wire 8 % P [7:0] $end
$var parameter 32 & CLOCK_PERIOD $end
$var reg 4 ' M [3:0] $end
$var reg 4 ( Q [3:0] $end
$var reg 1 ) clk $end
$var reg 1 * done_flag $end
$var reg 64 + end_time [63:0] $end
$var reg 1 , load $end
$var reg 3 - prev_count [2:0] $end
$var reg 1 . reset $end
$var reg 64 / start_time [63:0] $end
$var integer 32 0 iter_count [31:0] $end
$scope module dut $end
$var wire 4 1 M [3:0] $end
$var wire 4 2 Q [3:0] $end
$var wire 1 ) clk $end
$var wire 1 , load $end
$var wire 1 . reset $end
$var reg 4 3 A [3:0] $end
$var reg 3 4 Count [2:0] $end
$var reg 4 5 M_temp [3:0] $end
$var reg 8 6 P [7:0] $end
$var reg 1 7 Q_minus_one $end
$var reg 4 8 Q_temp [3:0] $end
$upscope $end
$upscope $end
$enddefinitions $end
$comment Show the parameter values. $end
$dumpall
b10100 &
$end
#0
$dumpvars
b0 8
07
bx 6
b0 5
b100 4
b0 3
b0 2
b0 1
b0 0
bx /
1.
b0 -
0,
bx +
0*
0)
b0 (
b0 '
bx %
b0 $
0#
b100 "
b0 !
$end
#10000
b0 %
b0 6
1)
#20000
0)
#30000
1)
#40000
0)
#50000
1)
#60000
0)
1,
b11 (
b11 2
b101 '
b101 1
0.
#70000
b100 -
b1000110 /
b11 %
b11 6
b101 5
b11 $
b11 8
1)
#80000
0)
0,
#90000
b11011001 %
b11011001 6
b11 "
b11 4
b1001 $
b1001 8
1#
17
b1101 !
b1101 3
1)
#100000
0)
#110000
b10 -
b10 0
b11101100 %
b11101100 6
b10 "
b10 4
b1110 !
b1110 3
b1100 $
b1100 8
1)
#120000
0)
#130000
b11110 %
b11110 6
b1 "
b1 4
b1110 $
b1110 8
0#
07
b1 !
b1 3
1)
#140000
0)
#150000
1*
b10010110 +
b1111 %
b1111 6
b0 "
b0 4
b0 !
b0 3
b1111 $
b1111 8
1)
#160000
0)
#170000
1)
#180000
0)
#190000
b0 -
b0 0
0*
b100 "
b100 4
b0 5
b0 $
b0 8
b0 %
b0 6
1)
1.
#200000
0)
#210000
b11 %
b11 6
b1011 5
b11 $
b11 8
b100 -
b11010010 /
1)
1,
b1011 '
b1011 1
0.
#220000
0)
#230000
b11 -
b1 0
b101001 %
b101001 6
b11 "
b11 4
b1001 $
b1001 8
1#
17
b10 !
b10 3
1)
0,
#240000
0)
#250000
b10100 %
b10100 6
b10 "
b10 4
b1 !
b1 3
b100 $
b100 8
1)
#260000
0)
#270000
b1 -
b11 0
b11100010 %
b11100010 6
b1 "
b1 4
b10 $
b10 8
0#
07
b1110 !
b1110 3
1)
#280000
0)
#290000
b11110001 %
b11110001 6
b0 "
b0 4
b1111 !
b1111 3
b1 $
b1 8
1)
#300000
0)
#310000
1*
b100110110 +
1)
#320000
0)
#330000
b100 "
b100 4
b0 5
b0 $
b0 8
b0 %
b0 6
b0 !
b0 3
b0 -
b0 0
0*
1)
1.
#340000
0)
#350000
b100 -
b101011110 /
b1011 %
b1011 6
b1010 5
b1011 $
b1011 8
1)
1,
b1011 (
b1011 2
b1010 '
b1010 1
0.
#360000
0)
#370000
b110101 %
b110101 6
b11 "
b11 4
b101 $
b101 8
1#
17
b11 !
b11 3
1)
0,
#380000
0)
#390000
b10 -
b10 0
b11010 %
b11010 6
b10 "
b10 4
b1 !
b1 3
b1010 $
b1010 8
1)
#400000
0)
#410000
b11011101 %
b11011101 6
b1 "
b1 4
b1101 $
b1101 8
0#
07
b1101 !
b1101 3
1)
#420000
0)
#430000
1*
b110101110 +
b11110 %
b11110 6
b0 "
b0 4
b1110 $
b1110 8
1#
17
b1 !
b1 3
1)
